{
  "owner": "gcp-scheduler",
  "timeZone": "UTC",
  "workerBaseUrlEnv": "STOCKVISION_WORKER_BASE_URL",
  "authTokenEnv": "SCHEDULER_AUTH_TOKEN",
  "jobs": [
    { "id": "intraday-check", "schedule": "* 1-5 * * 1-5", "task": "intraday-check", "description": "TW 09:00-13:30 intraday paper trading heartbeat" },
    { "id": "rescore-10", "schedule": "0 2 * * 1-5", "task": "intraday-rescore", "description": "TW 10:00 intraday ML re-score" },
    { "id": "rescore-11", "schedule": "0 3 * * 1-5", "task": "intraday-rescore", "description": "TW 11:00 intraday ML re-score" },
    { "id": "rescore-12", "schedule": "0 4 * * 1-5", "task": "intraday-rescore", "description": "TW 12:00 intraday ML re-score" },
    { "id": "rescore-1230", "schedule": "30 4 * * 1-5", "task": "intraday-rescore", "description": "TW 12:30 intraday ML re-score" },
    { "id": "eod-exit", "schedule": "25 5 * * 1-5", "task": "eod-exit", "description": "TW 13:25 EOD exit" },
    { "id": "daily-snapshot", "schedule": "20 6 * * 1-5", "task": "daily-snapshot", "description": "TW 14:20 paper account snapshot" },
    { "id": "evening-chain", "schedule": "15 9 * * 1-5", "task": "evening-chain", "query": "sync=1", "description": "TW 17:15 post-market event-driven chain: update -> indicators -> screener -> pipeline" },
    { "id": "ml-warmup", "schedule": "15 9 * * 1-5", "task": "ml-warmup", "description": "TW 17:15 ML controller health warmup" },
    { "id": "adapt", "schedule": "20 10 * * 1-5", "task": "adapt", "description": "TW 18:20 adaptive params update" },
    { "id": "daily-report", "schedule": "25 10 * * 1-5", "task": "daily-report", "description": "TW 18:25 daily report" },
    { "id": "weekly-audit", "schedule": "30 10 * * 5", "task": "weekly-audit", "description": "Friday TW 18:30 weekly audit" },
    { "id": "obsidian-sync", "schedule": "40 10 * * 1-5", "task": "obsidian-sync", "description": "TW 18:40 obsidian sync" },
    { "id": "regime-compute", "schedule": "50 10 * * 1-5", "task": "regime-compute", "description": "TW 18:50 regime compute" },
    { "id": "verify-v2", "schedule": "0 11 * * 1-5", "task": "verify-v2", "description": "TW 19:00 verify V2 and rolling IC refresh" },
    { "id": "model-ic-tracker", "schedule": "30 11 * * 5", "task": "model-ic-tracker", "description": "Friday TW 19:30 model IC tracker" },
    { "id": "debate-memory-retention", "schedule": "0 19 * * *", "task": "debate-memory-retention", "description": "TW 03:00 debate memory retention" },
    { "id": "weekly-cleanup", "schedule": "0 20 * * 6", "task": "weekly-cleanup", "description": "Sunday TW 04:00 weekly cleanup bundle" },
    { "id": "weekly-backtest", "schedule": "0 22 * * 6", "task": "weekly-backtest", "description": "Sunday TW 06:00 weekly backtest, MC, PBO" },
    { "id": "alpha-quality", "schedule": "0 22 * * 6", "task": "alpha-quality", "description": "Sunday TW 06:00 alpha quality refresh" },
    { "id": "weekly-optuna", "schedule": "30 22 * * 6", "task": "weekly-optuna", "description": "Sunday TW 06:30 weekly Optuna search" },
    { "id": "sector-leaders", "schedule": "30 22 * * 6", "task": "sector-leaders", "description": "Sunday TW 06:30 sector leader correlation refresh" },
    { "id": "monthly-optuna", "schedule": "first saturday of month 16:00", "task": "monthly-optuna", "description": "Monthly first Saturday UTC Optuna research sweep" },
    { "id": "monthly-retrain", "schedule": "first sunday of month 02:00", "timeZone": "Asia/Taipei", "task": "retrain", "query": "monthly=1", "description": "Monthly first Sunday TW 02:00 universal retrain lifecycle" },
    { "id": "optuna-queue", "schedule": "0 */6 * * *", "task": "optuna-queue", "description": "Every six hours Optuna queue processor" },
    { "id": "us-leading", "schedule": "30 22 * * 0-4", "task": "us-leading", "description": "TW 06:30 US leading signal" },
    { "id": "news-analyst", "schedule": "45 22 * * 0-4", "task": "news-analyst", "description": "TW 06:45 news analyst" },
    { "id": "morning-setup", "schedule": "15 23 * * 0-4", "task": "morning-setup", "description": "TW 07:15 morning setup and debate" },
    { "id": "morning-briefing", "schedule": "50 23 * * 0-4", "task": "morning-briefing", "description": "TW 07:50 morning briefing" },
    { "id": "pre-market-warmup", "schedule": "50 0 * * 1-5", "task": "pre-market-warmup", "description": "TW 08:50 control-plane drift and debate reconciliation" }
  ]
}
